hybrid_fuzzy_matcher/__init__.py
hybrid_fuzzy_matcher/matcher.py
hybrid_fuzzy_matcher-0.1.0.dist-info/licenses/LICENSE
hybrid_fuzzy_matcher-0.1.0.dist-info/METADATA
hybrid_fuzzy_matcher-0.1.0.dist-info/WHEEL
hybrid_fuzzy_matcher-0.1.0.dist-info/top_level.txt
hybrid_fuzzy_matcher-0.1.0.dist-info/RECORD
