Metadata-Version: 2.4
Name: hybrid-fuzzy-matcher
Version: 0.1.0
Summary: A robust fuzzy string matching library that combines syntactic and semantic approaches.
Author-email: Manoj Kumar <manojkumar.du.or.21@gmail.com>
Project-URL: Homepage, https://github.com/pypa/sampleproject
Project-URL: Bug Tracker, https://github.com/pypa/sampleproject/issues
Classifier: Programming Language :: Python :: 3
Classifier: License :: OSI Approved :: MIT License
Classifier: Operating System :: OS Independent
Requires-Python: >=3.8
License-File: LICENSE
Requires-Dist: thefuzz
Requires-Dist: sentence-transformers
Requires-Dist: torch
Requires-Dist: numpy
Requires-Dist: scikit-learn
Dynamic: license-file
